ibm_watson_pipelines/__init__.py
ibm_watson_pipelines/client.py
ibm_watson_pipelines/client_errors.py
ibm_watson_pipelines/cpd_paths.py
ibm_watson_pipelines/utils.py
ibm_watson_pipelines/version.py
ibm_watson_pipelines-1.0.4.dist-info/LICENSE
ibm_watson_pipelines-1.0.4.dist-info/METADATA
ibm_watson_pipelines-1.0.4.dist-info/WHEEL
ibm_watson_pipelines-1.0.4.dist-info/top_level.txt
ibm_watson_pipelines-1.0.4.dist-info/RECORD
