Metadata-Version: 2.1
Name: ibm-watson-pipelines
Version: 1.0.4
Summary: Python utilities for IBM Watson Pipelines
Home-page: https://www.ibm.com/docs/en/cloud-paks/cp-data/4.6.x?topic=functions-watson-pipelines
Author: Rafał Bigaj, Maksymilian Erazmus
Author-email: rafal.bigaj@pl.ibm.com, maksymilian.erazmus1@pl.ibm.com
Classifier: Programming Language :: Python :: 3
Classifier: License :: OSI Approved :: MIT License
Classifier: Operating System :: OS Independent
Requires-Python: >=3.7
License-File: LICENSE
Requires-Dist: ibm-cloud-sdk-core >=3.11.3
Requires-Dist: ibm-cos-sdk >=2.10.0
Requires-Dist: attrs >=21.2.0
Requires-Dist: kfp <2.0.0,>=1.8.22
Requires-Dist: requests >=2.25.1
Requires-Dist: responses >=0.13.4
Requires-Dist: pytest >=6.2.5
Requires-Dist: typing-extensions >=3.7.4
Requires-Dist: urllib3 >=1.26.17
